setup.py
batch_sms/__init__.py
batch_sms/associated_batch_sender.py
batch_sms/batch_sender.py
batch_sms/batch_sms.py
batch_sms/sender.py
batch_sms/simple_batch_sender.py
batch_sms/twilio_sender.py
batch_sms.egg-info/PKG-INFO
batch_sms.egg-info/SOURCES.txt
batch_sms.egg-info/dependency_links.txt
batch_sms.egg-info/requires.txt
batch_sms.egg-info/top_level.txt