Metadata-Version: 1.0
Name: batch-sms
Version: 0.1.0
Summary: Library to send large numbers of text messages.
Home-page: https://github.com/csu/batch_sms
Author: Christopher Su
Author-email: chris+py@christopher.su
License: UNKNOWN
Platform: UNKNOWN
